LICENSE.md
pekora/__init__.py
pekora/callbacks.py
pekora/cli.py
pekora/context.py
pekora/exceptions.py
pekora/models.py
pekora/peko.py
pekora/prefs.py
pekora/prompts.py
pekora/utils.py
pekora-1.0.5.dist-info/entry_points.txt
pekora-1.0.5.dist-info/WHEEL
pekora-1.0.5.dist-info/LICENSE.md
pekora-1.0.5.dist-info/METADATA
pekora-1.0.5.dist-info/RECORD
